opencnam/__init__.py
opencnam/errors.py
opencnam/opencnam.py
tests/__init__.py
tests/test_opencnam.py
opencnam-0.7.dist-info/METADATA
opencnam-0.7.dist-info/WHEEL
opencnam-0.7.dist-info/top_level.txt
opencnam-0.7.dist-info/RECORD
