Metadata-Version: 2.1
Name: opencnam
Version: 0.7
Summary: A simple python library for getting caller ID name information using the opencnam API.
Home-page: http://www.opencnam.com
Author: Jason Rudder
Author-email: jason.rudder@telo.com
License: UNLICENSE
Keywords: voip http api rest caller id name cid cnam telephony telephone python library
Platform: UNKNOWN
Classifier: Development Status :: 5 - Production/Stable
Classifier: Environment :: Console
Classifier: Intended Audience :: Developers
Classifier: Intended Audience :: Telecommunications Industry
Classifier: License :: Public Domain
Classifier: Natural Language :: English
Classifier: Operating System :: POSIX :: Linux
Classifier: Programming Language :: Python :: 2.7
Classifier: Programming Language :: Python :: 3.7
Classifier: Programming Language :: Python :: Implementation :: CPython
Classifier: Topic :: Communications
Classifier: Topic :: Communications :: Internet Phone
Classifier: Topic :: Communications :: Telephony
Classifier: Topic :: Internet
Classifier: Topic :: Utilities
Requires-Dist: requests (>=2.20.1)
